MANIFEST.in
README.md
pyproxy.py
setup.py
pyproxy.egg-info/PKG-INFO
pyproxy.egg-info/SOURCES.txt
pyproxy.egg-info/dependency_links.txt
pyproxy.egg-info/entry_points.txt
pyproxy.egg-info/requires.txt
pyproxy.egg-info/top_level.txt