Metadata-Version: 1.1
Name: pyproxy
Version: 0.1.6
Summary: HTTP(s) proxy server base on tornado, in one file!
Home-page: https://github.com/binux/pyproxy
Author: Roy Binux
Author-email: roy@binux.me
License: Apache License, Version 2.0
Keywords: proxy https http
Platform: UNKNOWN
Classifier: Development Status :: 4 - Beta
Classifier: Programming Language :: Python :: 2
Classifier: Programming Language :: Python :: 2.6
Classifier: Programming Language :: Python :: 2.7
Classifier: Programming Language :: Python :: 3
Classifier: Programming Language :: Python :: 3.3
Classifier: Programming Language :: Python :: 3.4
Classifier: License :: OSI Approved :: Apache Software License
Classifier: Intended Audience :: Developers
Classifier: Operating System :: OS Independent
Classifier: Topic :: Internet :: WWW/HTTP
